cobra_ai/__init__.py
cobra_ai/model/__init__.py
cobra_ai/model/adv_vae.py
cobra_ai/model/cobra.py
cobra_ai/model/onto_vae.py
cobra_ai/model/vanilla_vae.py
cobra_ai/module/__init__.py
cobra_ai/module/autotune.py
cobra_ai/module/decorators.py
cobra_ai/module/metrics.py
cobra_ai/module/modules.py
cobra_ai/module/ontobj.py
cobra_ai/module/ontobj_utils.py
cobra_ai/module/utils.py
cobra_ai/vignettes/__init__.py
cobra_ai/vignettes/autotune.ipynb
cobra_ai/vignettes/create_ontobj.ipynb
cobra_ai/vignettes/train_model.ipynb
cobra_ai-0.1.0.dist-info/LICENSE
cobra_ai-0.1.0.dist-info/METADATA
cobra_ai-0.1.0.dist-info/WHEEL
cobra_ai-0.1.0.dist-info/RECORD
