Metadata-Version: 2.1
Name: cobra-ai
Version: 0.1.0
Summary: Package to preprocess ontologies, train OntoVAE and COBRA models and obtain TF and pathway activities.
Home-page: https://github.com/hdsu-bioquant/cobra-ai
License: GPLv3
Author: daria-dc
Author-email: daria.doncevic@gmail.com
Requires-Python: >=3.10,<4.0
Classifier: License :: Other/Proprietary License
Classifier: Programming Language :: Python :: 3
Classifier: Programming Language :: Python :: 3.10
Classifier: Programming Language :: Python :: 3.11
Classifier: Programming Language :: Python :: 3.12
Classifier: Programming Language :: Python :: 3.13
Requires-Dist: colorcet (>=3.1.0)
Requires-Dist: goatools (>=1.4.12)
Requires-Dist: hyperopt (>=0.2.7)
Requires-Dist: numpy (<2.0)
Requires-Dist: pandas (>=2.2.3)
Requires-Dist: ray (>=2.38.0)
Requires-Dist: scanpy (>=1.10.3)
Requires-Dist: seaborn (>=0.13.2)
Requires-Dist: torch (>=1.13.1)
Requires-Dist: tqdm (>=4.64.1)
Project-URL: Repository, https://github.com/hdsu-bioquant/cobra-ai
